oracle_parquet_exporter/__init__.py
oracle_parquet_exporter/main.py
oracle_parquet_exporter-0.0.22.dist-info/licenses/LICENSE
oracle_parquet_exporter-0.0.22.dist-info/METADATA
oracle_parquet_exporter-0.0.22.dist-info/WHEEL
oracle_parquet_exporter-0.0.22.dist-info/entry_points.txt
oracle_parquet_exporter-0.0.22.dist-info/top_level.txt
oracle_parquet_exporter-0.0.22.dist-info/RECORD
