Metadata-Version: 2.4
Name: oracle-parquet-exporter
Version: 0.0.22
Summary: A Python-based tool for exporting Oracle database table data to parquet files
Author-email: Philip Moore <philip@gizmodata.com>
License-Expression: Apache-2.0
Project-URL: Homepage, https://github.com/gizmodata/oracle-parquet-exporter
Keywords: oracle,parquet,exporter,data,export,apache,arrow
Classifier: Programming Language :: Python
Classifier: Programming Language :: Python :: 3
Requires-Python: >=3.10
License-File: LICENSE
Requires-Dist: oracledb==3.1.*
Requires-Dist: pyarrow==20.0.*
Requires-Dist: click==8.2.*
Requires-Dist: codetiming==1.4.*
Requires-Dist: munch==4.0.*
Requires-Dist: python-dateutil==2.9.*
Requires-Dist: pytz==2025.*
Requires-Dist: python-dotenv==1.1.*
Provides-Extra: test
Requires-Dist: pytest; extra == "test"
Requires-Dist: pytest-snapshot; extra == "test"
Requires-Dist: pytest-mock; extra == "test"
Requires-Dist: filelock; extra == "test"
Requires-Dist: dask; extra == "test"
Requires-Dist: distributed; extra == "test"
Requires-Dist: pins[gcs]; extra == "test"
Requires-Dist: docker; extra == "test"
Provides-Extra: dev
Requires-Dist: bumpver; extra == "dev"
Requires-Dist: pip-tools; extra == "dev"
Requires-Dist: pytest; extra == "dev"
Dynamic: license-file
